Gresec/__init__.py
Gresec/database.py
Gresec/main.py
Gresec/scraper.py
GreSec-0.1.dist-info/METADATA
GreSec-0.1.dist-info/WHEEL
GreSec-0.1.dist-info/top_level.txt
GreSec-0.1.dist-info/RECORD
