Metadata-Version: 2.1
Name: GreSec
Version: 0.1
Summary: A package for checking suspicious contracts
Home-page: UNKNOWN
Author: AkashGreninja
Author-email: akashuhulekal@gmail.com
License: UNKNOWN
Platform: UNKNOWN
Requires-Dist: bs4
Requires-Dist: fastapi
Requires-Dist: pymongo
Requires-Dist: python-dotenv
Requires-Dist: requests
